pykg2tbl/__init__.py
pykg2tbl/__main__.py
pykg2tbl/__version__.py
pykg2tbl/exceptions.py
pykg2tbl/kg2tbl.py
pykg2tbl/query.py
pykg2tbl/sparql_templates/all.sparql
pykg2tbl/sparql_templates/bodc-find.sparql
pykg2tbl/sparql_templates/bodc-listing.sparql
pykg2tbl/sparql_templates/broader-terms.sparql
pykg2tbl/sparql_templates/rdf-predicates-count.sparql
pykg2tbl/sparql_templates/rdf-predicates.sparql
pykg2tbl/sparql_templates/rdf-types.sparql
pykg2tbl/sparql_templates/skos-broader-depth.sparql
pykg2tbl/sparql_templates/skos-collection-member-count.sparql
pykg2tbl/sparql_templates/skos-collection.sparql
pykg2tbl/sparql_templates/term-match-in-collection.sparql
pykg2tbl-0.0.2.dist-info/LICENSE
pykg2tbl-0.0.2.dist-info/METADATA
pykg2tbl-0.0.2.dist-info/WHEEL
pykg2tbl-0.0.2.dist-info/entry_points.txt
pykg2tbl-0.0.2.dist-info/RECORD
