Metadata-Version: 2.1
Name: pykg2tbl
Version: 0.0.2
Summary: Py Project to extract table data from knowwledge-graphs using sparql templates
Home-page: https://github.com/vliz-be-opsci/pykg2tbl
License: MIT
Author: Marc Portier
Author-email: marc.portier@gmail.com
Maintainer: João dos Santos
Maintainer-email: jotaflame@gmail.com
Requires-Python: >=3.8.1,<4.0.0
Classifier: License :: OSI Approved :: MIT License
Classifier: Programming Language :: Python
Classifier: Programming Language :: Python :: 3
Classifier: Programming Language :: Python :: 3.9
Classifier: Programming Language :: Python :: 3.10
Classifier: Programming Language :: Python :: 3.11
Classifier: Programming Language :: Python :: 3.8
Requires-Dist: argparse
Requires-Dist: pandas
Requires-Dist: pyrdfj2
Requires-Dist: rdflib
Requires-Dist: sparqlwrapper
Requires-Dist: validators
Project-URL: Repository, https://github.com/vliz-be-opsci/pykg2tbl
